<?xml version="1.0" encoding="utf-8"?>
<!DOCTYPE hibernate-mapping PUBLIC "-//Hibernate/Hibernate Mapping DTD 3.0//EN"
"http://hibernate.sourceforge.net/hibernate-mapping-3.0.dtd">
<!-- 
    Mapping file autogenerated by MyEclipse Persistence Tools
-->
<hibernate-mapping>
    <class name="org.model.Administrator" table="administrator" catalog="e_book">
        <id name="administratorId" type="java.lang.Integer">
            <column name="administrator_id" />
            <generator class="native" />
        </id>
        <property name="administratorName" type="java.lang.String">
            <column name="administrator_name" not-null="true">
                <comment>管理员姓名</comment>
            </column>
        </property>
        <property name="administratorPassword" type="java.lang.String">
            <column name="administrator_password" not-null="true">
                <comment>管理员密码</comment>
            </column>
        </property>
    </class>
</hibernate-mapping>
